huaweicloudsdksms/__init__.py
huaweicloudsdksms/v3/__init__.py
huaweicloudsdksms/v3/sms_async_client.py
huaweicloudsdksms/v3/sms_client.py
huaweicloudsdksms/v3/model/__init__.py
huaweicloudsdksms/v3/model/batch_consistency_req.py
huaweicloudsdksms/v3/model/batch_get_consistency_result_req.py
huaweicloudsdksms/v3/model/btrfs_file_system.py
huaweicloudsdksms/v3/model/btrfs_subvolumn.py
huaweicloudsdksms/v3/model/check_net_acl_request.py
huaweicloudsdksms/v3/model/check_net_acl_response.py
huaweicloudsdksms/v3/model/clone_server.py
huaweicloudsdksms/v3/model/clone_server_brief.py
huaweicloudsdksms/v3/model/collect_log_request.py
huaweicloudsdksms/v3/model/collect_log_response.py
huaweicloudsdksms/v3/model/command_body.py
huaweicloudsdksms/v3/model/command_param.py
huaweicloudsdksms/v3/model/config_body.py
huaweicloudsdksms/v3/model/configuration_request_body.py
huaweicloudsdksms/v3/model/consistency_result.py
huaweicloudsdksms/v3/model/consistency_result_request_body_result_list.py
huaweicloudsdksms/v3/model/create_migproject_request.py
huaweicloudsdksms/v3/model/create_migproject_response.py
huaweicloudsdksms/v3/model/create_privacy_agreements_request.py
huaweicloudsdksms/v3/model/create_privacy_agreements_response.py
huaweicloudsdksms/v3/model/create_task_request.py
huaweicloudsdksms/v3/model/create_task_response.py
huaweicloudsdksms/v3/model/create_template_req.py
huaweicloudsdksms/v3/model/create_template_request.py
huaweicloudsdksms/v3/model/create_template_response.py
huaweicloudsdksms/v3/model/delete_ids.py
huaweicloudsdksms/v3/model/delete_migproject_request.py
huaweicloudsdksms/v3/model/delete_migproject_response.py
huaweicloudsdksms/v3/model/delete_server_request.py
huaweicloudsdksms/v3/model/delete_server_response.py
huaweicloudsdksms/v3/model/delete_servers_request.py
huaweicloudsdksms/v3/model/delete_servers_response.py
huaweicloudsdksms/v3/model/delete_task_request.py
huaweicloudsdksms/v3/model/delete_task_response.py
huaweicloudsdksms-3.1.184.dist-info/METADATA
huaweicloudsdksms-3.1.184.dist-info/WHEEL
huaweicloudsdksms-3.1.184.dist-info/licenses/LICENSE
huaweicloudsdksms-3.1.184.dist-info/RECORD
